tutornudge/__about__.py
tutornudge/__init__.py
tutornudge/plugin.py
tutornudge/patches/.gitignore
tutornudge/patches/k8s-jobs
tutornudge/templates/nudge/build/.gitignore
tutornudge/templates/nudge/tasks/.gitignore
tutor_contrib_nudge-19.0.0.dist-info/METADATA
tutor_contrib_nudge-19.0.0.dist-info/WHEEL
tutor_contrib_nudge-19.0.0.dist-info/entry_points.txt
tutor_contrib_nudge-19.0.0.dist-info/top_level.txt
tutor_contrib_nudge-19.0.0.dist-info/RECORD
